Metadata-Version: 2.4
Name: swh.objstorage
Version: 5.1.0
Summary: Software Heritage object storage
Author-email: Software Heritage developers <swh-devel@inria.fr>
Project-URL: Homepage, https://gitlab.softwareheritage.org/swh/devel/swh-objstorage
Project-URL: Bug Reports, https://gitlab.softwareheritage.org/swh/devel/swh-objstorage/-/issues
Project-URL: Funding, https://www.softwareheritage.org/donate
Project-URL: Documentation, https://docs.softwareheritage.org/devel/swh-objstorage/
Project-URL: Source, https://gitlab.softwareheritage.org/swh/devel/swh-objstorage.git
Classifier: Programming Language :: Python :: 3
Classifier: Intended Audience :: Developers
Classifier: License :: OSI Approved :: GNU General Public License v3 (GPLv3)
Classifier: Operating System :: OS Independent
Classifier: Development Status :: 5 - Production/Stable
Classifier: Programming Language :: Python :: Implementation :: CPython
Classifier: Programming Language :: Python :: Implementation :: PyPy
Requires-Python: >=3.11
License-File: LICENSE
License-File: AUTHORS
Requires-Dist: click
Requires-Dist: deprecated
Requires-Dist: msgpack
Requires-Dist: requests
Requires-Dist: swh.core[http]>=3.0.0
Requires-Dist: swh.model>=8.4.0
Requires-Dist: swh.shard>=1.0.0
Provides-Extra: azure
Requires-Dist: azure-storage-blob!=12.9.0,>=12.0; extra == "azure"
Provides-Extra: libcloud
Requires-Dist: apache-libcloud; extra == "libcloud"
Provides-Extra: winery
Requires-Dist: psycopg[c,pool]; extra == "winery"
Requires-Dist: systemd-python; extra == "winery"
Provides-Extra: testing
Requires-Dist: moto[s3,server]; extra == "testing"
Requires-Dist: pytest>=8.1; extra == "testing"
Requires-Dist: pytest-mock; extra == "testing"
Requires-Dist: requests_mock[fixture]>=1.9; extra == "testing"
Requires-Dist: requests_toolbelt; extra == "testing"
Requires-Dist: swh.core[testing]>=3.0.0; extra == "testing"
Requires-Dist: types-pyyaml; extra == "testing"
Requires-Dist: types-requests; extra == "testing"
Requires-Dist: pytest-postgresql>5; extra == "testing"
Requires-Dist: msgpack-types; extra == "testing"
Requires-Dist: azure-storage-blob!=12.9.0,>=12.0; extra == "testing"
Requires-Dist: apache-libcloud; extra == "testing"
Requires-Dist: psycopg[c,pool]; extra == "testing"
Requires-Dist: systemd-python; extra == "testing"
Dynamic: license-file
